<?xml version="1.0" encoding="utf-8" ?>
<GlobalConfigData>
	<ScreenType>Level</ScreenType>
	<!--<ScreenType>Play</ScreenType>-->
	<!--<ScreenType>Diff</ScreenType>-->
	<!--<ScreenType>Level</ScreenType>-->
	<FramesPerSecond>100</FramesPerSecond>
	<MaximLevel>16</MaximLevel>
	<LoadAudio>false</LoadAudio>
	<PlayAudio>true</PlayAudio>
	<SplashDelay>0</SplashDelay>
	<StarDelay>2000</StarDelay>
	<GridDelay>200</GridDelay>
	<SelectDelay>500</SelectDelay>
	<ScoreDelay>800</ScoreDelay>
	<EventRatio>1.0</EventRatio>
	<ScoreBlink>false</ScoreBlink>
	<UpdateStar>false</UpdateStar>
	<UpdateGrid>false</UpdateGrid>
	<RenderBack>true</RenderBack>
	<RenderIcon>true</RenderIcon>
	<TargetX>0</TargetX>
	<TargetY>0</TargetY>
	<EnemysX>160</EnemysX>
	<EnemysY>160</EnemysY>
	<EnemyFrame>7</EnemyFrame>
	<EnemyIndex>0</EnemyIndex>
	<EnemySpawn>3</EnemySpawn>
	<EnemyTotal>10</EnemyTotal>
	<IsGodMode>true</IsGodMode>
	<QuitsToExit>true</QuitsToExit>
</GlobalConfigData>